livekit/__init__.py
livekit/plugins/__init__.py
livekit/plugins/langgraph/__init__.py
livekit/plugins/langgraph/langgraph.py
livekit/plugins/langgraph/py.typed
livekit_plugins_langgraph-0.1.1.dist-info/METADATA
livekit_plugins_langgraph-0.1.1.dist-info/WHEEL
livekit_plugins_langgraph-0.1.1.dist-info/licenses/LICENSE
livekit_plugins_langgraph-0.1.1.dist-info/RECORD
