Metadata-Version: 2.4
Name: livekit-plugins-langgraph
Version: 0.1.1
Summary: Universal LiveKit plugin for LangGraph workflows with intelligent filtering
Project-URL: Homepage, https://github.com/tim-yung/livekit-plugins-langgraph
Project-URL: Repository, https://github.com/tim-yung/livekit-plugins-langgraph
Project-URL: Documentation, https://github.com/tim-yung/livekit-plugins-langgraph#readme
Project-URL: Issues, https://github.com/tim-yung/livekit-plugins-langgraph/issues
Author-email: Tim Yung <yungkaitim@gmail.com>
License-Expression: MIT
License-File: LICENSE
Keywords: agents,ai,langgraph,livekit,multiagent,voice
Classifier: Development Status :: 4 - Beta
Classifier: Intended Audience :: Developers
Classifier: License :: OSI Approved :: MIT License
Classifier: Programming Language :: Python :: 3
Classifier: Programming Language :: Python :: 3.9
Classifier: Programming Language :: Python :: 3.10
Classifier: Programming Language :: Python :: 3.11
Classifier: Programming Language :: Python :: 3.12
Classifier: Programming Language :: Python :: 3.13
Classifier: Topic :: Scientific/Engineering :: Artificial Intelligence
Classifier: Topic :: Software Development :: Libraries :: Python Modules
Requires-Python: >=3.9
Requires-Dist: langchain-core>=0.3.0
Requires-Dist: langchain-openai>=0.3.22
Requires-Dist: langgraph-sdk>=0.1.0
Requires-Dist: langgraph>=0.2.0
Requires-Dist: livekit-agents>=0.8.0
Requires-Dist: livekit-plugins-deepgram>=1.1.1
Requires-Dist: livekit-plugins-silero>=1.1.1
Requires-Dist: livekit-plugins-turn-detector>=1.1.1
Requires-Dist: python-dotenv>=1.1.0
Provides-Extra: dev
Requires-Dist: black>=23.0.0; extra == 'dev'
Requires-Dist: isort>=5.12.0; extra == 'dev'
Requires-Dist: mypy>=1.0.0; extra == 'dev'
Requires-Dist: pytest-asyncio>=1.0.0; extra == 'dev'
Requires-Dist: pytest>=8.4.0; extra == 'dev'
Requires-Dist: twine>=6.1.0; extra == 'dev'
Provides-Extra: examples
Requires-Dist: langchain-openai>=0.3.0; extra == 'examples'
Requires-Dist: livekit-agents>=0.8.0; extra == 'examples'
Requires-Dist: livekit-plugins-deepgram>=0.6.0; extra == 'examples'
Requires-Dist: livekit-plugins-silero>=0.6.0; extra == 'examples'
Requires-Dist: livekit-plugins-turn-detector>=0.1.0; extra == 'examples'
Requires-Dist: python-dotenv>=1.0.0; extra == 'examples'
